{"studentId":"synthetic-browser-generator","timestampUtc":"2026-02-21T05:15:01.537591+00:00","screenFrameHash":"0018083C3CFF7E7E","frameChanged":true,"activeProcessName":"outlook","activeWindowTitle":"Operations dashboard","browserHintUrl":"https://portal.example.com/monitoring","detection":{"isAiUiDetected":false,"confidence":0.034,"class":"None","stageSource":"MetadataRule","reason":"Synthetic sample (template_renderer)","modelVersion":"synthetic-browser-v2","isStable":false,"triggeredKeywords":null}}