{"studentId":"synthetic-browser-generator","timestampUtc":"2026-02-21T04:50:35.537591+00:00","screenFrameHash":"007F3C7F7EFFFFFF","frameChanged":true,"activeProcessName":"outlook","activeWindowTitle":"Operations dashboard","browserHintUrl":"https://portal.example.com/monitoring","detection":{"isAiUiDetected":false,"confidence":0.017,"class":"None","stageSource":"MetadataRule","reason":"Synthetic sample (template_renderer)","modelVersion":"synthetic-browser-v2","isStable":false,"triggeredKeywords":null}}