{"studentId":"synthetic-browser-generator","timestampUtc":"2026-02-21T04:50:28.537591+00:00","screenFrameHash":"00C0FCF8F8FEFC00","frameChanged":true,"activeProcessName":"chrome","activeWindowTitle":"Perplexity - Perplexity","browserHintUrl":"https://perplexity.ai/?q=Generate+test+cases","detection":{"isAiUiDetected":true,"confidence":0.935,"class":"Perplexity","stageSource":"OnnxMulticlass","reason":"Synthetic sample (template_renderer)","modelVersion":"synthetic-browser-v2","isStable":true,"triggeredKeywords":null}}